{
  "d01c1dff24268d4d42413dedfe2aafc0": {
    "scheme": "nano-session",
    "network": "nano:mainnet",
    "asset": "XNO",
    "amount": "10000000000000000000000000000",
    "payTo": "nano_39qdd16muqpz78fk5nxsaqpd1dxko54hbiic7nrirwkjei49f3ir439isxgx",
    "maxTimeoutSeconds": 600,
    "extra": {
      "tag": 246344,
      "sessionId": "d01c1dff24268d4d42413dedfe2aafc0",
      "tagModulus": 1000000,
      "expiresAt": "2026-03-03T04:50:17.566Z"
    }
  },
  "d855ae2a03afb091209ee464c49aa160": {
    "scheme": "nano-session",
    "network": "nano:mainnet",
    "asset": "XNO",
    "amount": "10000000000000000000000000000",
    "payTo": "nano_39qdd16muqpz78fk5nxsaqpd1dxko54hbiic7nrirwkjei49f3ir439isxgx",
    "maxTimeoutSeconds": 600,
    "extra": {
      "tag": 486465,
      "sessionId": "d855ae2a03afb091209ee464c49aa160",
      "tagModulus": 1000000,
      "expiresAt": "2026-03-03T04:52:17.936Z"
    }
  },
  "2d6a3924abf0e6959b52a407e3f4073d": {
    "scheme": "nano-session",
    "network": "nano:mainnet",
    "asset": "XNO",
    "amount": "10000000000000000000000000000",
    "payTo": "nano_39qdd16muqpz78fk5nxsaqpd1dxko54hbiic7nrirwkjei49f3ir439isxgx",
    "maxTimeoutSeconds": 600,
    "extra": {
      "tag": 26001,
      "sessionId": "2d6a3924abf0e6959b52a407e3f4073d",
      "tagModulus": 1000000,
      "expiresAt": "2026-03-03T04:52:59.837Z"
    }
  },
  "d8b5e6bc89525b12926faa761ab13c92": {
    "scheme": "nano-session",
    "network": "nano:mainnet",
    "asset": "XNO",
    "amount": "10000000000000000000000000000",
    "payTo": "nano_39qdd16muqpz78fk5nxsaqpd1dxko54hbiic7nrirwkjei49f3ir439isxgx",
    "maxTimeoutSeconds": 600,
    "extra": {
      "tag": 568812,
      "sessionId": "d8b5e6bc89525b12926faa761ab13c92",
      "tagModulus": 1000000,
      "expiresAt": "2026-03-03T05:00:57.174Z"
    }
  },
  "35142498c06e8642a28bdd795becdabc": {
    "scheme": "nano-session",
    "network": "nano:mainnet",
    "asset": "XNO",
    "amount": "10000000000000000000000000000",
    "payTo": "nano_39qdd16muqpz78fk5nxsaqpd1dxko54hbiic7nrirwkjei49f3ir439isxgx",
    "maxTimeoutSeconds": 600,
    "extra": {
      "tag": 364140,
      "sessionId": "35142498c06e8642a28bdd795becdabc",
      "tagModulus": 1000000,
      "expiresAt": "2026-03-03T05:44:17.506Z"
    }
  },
  "9fb2cd57fb13400b0baddf6607fa852e": {
    "scheme": "nano-session",
    "network": "nano:mainnet",
    "asset": "XNO",
    "amount": "10000000000000000000000000000",
    "payTo": "nano_39qdd16muqpz78fk5nxsaqpd1dxko54hbiic7nrirwkjei49f3ir439isxgx",
    "maxTimeoutSeconds": 600,
    "extra": {
      "tag": 858547,
      "sessionId": "9fb2cd57fb13400b0baddf6607fa852e",
      "tagModulus": 1000000,
      "expiresAt": "2026-03-03T05:44:49.216Z"
    }
  },
  "b930c44a1655edcd71a5295ed56ee32b": {
    "scheme": "nano-session",
    "network": "nano:mainnet",
    "asset": "XNO",
    "amount": "10000000000000000000000000000",
    "payTo": "nano_39qdd16muqpz78fk5nxsaqpd1dxko54hbiic7nrirwkjei49f3ir439isxgx",
    "maxTimeoutSeconds": 600,
    "extra": {
      "tag": 94122,
      "sessionId": "b930c44a1655edcd71a5295ed56ee32b",
      "tagModulus": 1000000,
      "expiresAt": "2026-03-03T06:00:15.443Z"
    }
  },
  "cf726e93762c4db0d830ad670f9f3148": {
    "scheme": "nano-session",
    "network": "nano:mainnet",
    "asset": "XNO",
    "amount": "10000000000000000000000000000",
    "payTo": "nano_39qdd16muqpz78fk5nxsaqpd1dxko54hbiic7nrirwkjei49f3ir439isxgx",
    "maxTimeoutSeconds": 600,
    "extra": {
      "tag": 750519,
      "sessionId": "cf726e93762c4db0d830ad670f9f3148",
      "tagModulus": 1000000,
      "expiresAt": "2026-03-03T06:04:31.237Z"
    }
  },
  "8a8e058cfbce8c2e9053d107841c98db": {
    "scheme": "nano-session",
    "network": "nano:mainnet",
    "asset": "XNO",
    "amount": "10000000000000000000000000000",
    "payTo": "nano_39qdd16muqpz78fk5nxsaqpd1dxko54hbiic7nrirwkjei49f3ir439isxgx",
    "maxTimeoutSeconds": 600,
    "extra": {
      "tag": 679447,
      "sessionId": "8a8e058cfbce8c2e9053d107841c98db",
      "tagModulus": 1000000,
      "expiresAt": "2026-03-03T06:07:37.270Z"
    }
  },
  "f8f99c5d55e5ba4f0136d873e2195012": {
    "scheme": "nano-session",
    "network": "nano:mainnet",
    "asset": "XNO",
    "amount": "10000000000000000000000000000",
    "payTo": "nano_39qdd16muqpz78fk5nxsaqpd1dxko54hbiic7nrirwkjei49f3ir439isxgx",
    "maxTimeoutSeconds": 600,
    "extra": {
      "tag": 930741,
      "sessionId": "f8f99c5d55e5ba4f0136d873e2195012",
      "tagModulus": 1000000,
      "expiresAt": "2026-03-03T06:09:54.527Z"
    }
  },
  "a3823c166de31ec86317e0de41636500": {
    "scheme": "nano-session",
    "network": "nano:mainnet",
    "asset": "XNO",
    "amount": "10000000000000000000000000000",
    "payTo": "nano_39qdd16muqpz78fk5nxsaqpd1dxko54hbiic7nrirwkjei49f3ir439isxgx",
    "maxTimeoutSeconds": 600,
    "extra": {
      "tag": 851570,
      "sessionId": "a3823c166de31ec86317e0de41636500",
      "tagModulus": 1000000,
      "expiresAt": "2026-03-03T07:20:10.194Z"
    }
  },
  "a89046034592071bfe65a97cd35dd006": {
    "scheme": "nano-session",
    "network": "nano:mainnet",
    "asset": "XNO",
    "amount": "10000000000000000000000000000",
    "payTo": "nano_39qdd16muqpz78fk5nxsaqpd1dxko54hbiic7nrirwkjei49f3ir439isxgx",
    "maxTimeoutSeconds": 600,
    "extra": {
      "tag": 31187,
      "sessionId": "a89046034592071bfe65a97cd35dd006",
      "tagModulus": 1000000,
      "expiresAt": "2026-03-03T07:31:18.983Z"
    }
  },
  "d0f331690b6cee5b0ea9d8d3ecbbb2ec": {
    "scheme": "nano-session",
    "network": "nano:mainnet",
    "asset": "XNO",
    "amount": "10000000000000000000000000000",
    "payTo": "nano_39qdd16muqpz78fk5nxsaqpd1dxko54hbiic7nrirwkjei49f3ir439isxgx",
    "maxTimeoutSeconds": 600,
    "extra": {
      "tag": 467225,
      "sessionId": "d0f331690b6cee5b0ea9d8d3ecbbb2ec",
      "tagModulus": 1000000,
      "expiresAt": "2026-03-03T08:00:28.137Z"
    }
  },
  "acff1f4517c2b97be451361fb6122abb": {
    "scheme": "nano-session",
    "network": "nano:mainnet",
    "asset": "XNO",
    "amount": "10000000000000000000000000000",
    "payTo": "nano_39qdd16muqpz78fk5nxsaqpd1dxko54hbiic7nrirwkjei49f3ir439isxgx",
    "maxTimeoutSeconds": 600,
    "extra": {
      "tag": 600605,
      "sessionId": "acff1f4517c2b97be451361fb6122abb",
      "tagModulus": 1000000,
      "expiresAt": "2026-03-03T08:04:14.362Z"
    }
  },
  "aff2f48bf38ba95909ae83001f5cf5b9": {
    "scheme": "nano-session",
    "network": "nano:mainnet",
    "asset": "XNO",
    "amount": "10000000000000000000000000000",
    "payTo": "nano_39qdd16muqpz78fk5nxsaqpd1dxko54hbiic7nrirwkjei49f3ir439isxgx",
    "maxTimeoutSeconds": 600,
    "extra": {
      "tag": 335234,
      "sessionId": "aff2f48bf38ba95909ae83001f5cf5b9",
      "tagModulus": 1000000,
      "expiresAt": "2026-03-03T08:04:24.400Z"
    }
  },
  "bdd48213ae17a8830738ab852c78b4ad": {
    "scheme": "nano-session",
    "network": "nano:mainnet",
    "asset": "XNO",
    "amount": "10000000000000000000000000000",
    "payTo": "nano_39qdd16muqpz78fk5nxsaqpd1dxko54hbiic7nrirwkjei49f3ir439isxgx",
    "maxTimeoutSeconds": 600,
    "extra": {
      "tag": 858530,
      "sessionId": "bdd48213ae17a8830738ab852c78b4ad",
      "tagModulus": 1000000,
      "expiresAt": "2026-03-03T08:04:27.841Z"
    }
  },
  "cd4574492bc6f3dd850d633f23846459": {
    "scheme": "nano-session",
    "network": "nano:mainnet",
    "asset": "XNO",
    "amount": "10000000000000000000000000000",
    "payTo": "nano_39qdd16muqpz78fk5nxsaqpd1dxko54hbiic7nrirwkjei49f3ir439isxgx",
    "maxTimeoutSeconds": 600,
    "extra": {
      "tag": 414353,
      "sessionId": "cd4574492bc6f3dd850d633f23846459",
      "tagModulus": 1000000,
      "expiresAt": "2026-03-03T08:04:31.685Z"
    }
  },
  "385fe832851388aa0fc86029c4c04045": {
    "scheme": "nano-session",
    "network": "nano:mainnet",
    "asset": "XNO",
    "amount": "10000000000000000000000000000",
    "payTo": "nano_39qdd16muqpz78fk5nxsaqpd1dxko54hbiic7nrirwkjei49f3ir439isxgx",
    "maxTimeoutSeconds": 600,
    "extra": {
      "tag": 576541,
      "sessionId": "385fe832851388aa0fc86029c4c04045",
      "tagModulus": 1000000,
      "expiresAt": "2026-03-03T08:05:33.319Z"
    }
  },
  "a023cfcb88cb72ab0f689ad3ab7d1e92": {
    "scheme": "nano-session",
    "network": "nano:mainnet",
    "asset": "XNO",
    "amount": "10000000000000000000000000000",
    "payTo": "nano_39qdd16muqpz78fk5nxsaqpd1dxko54hbiic7nrirwkjei49f3ir439isxgx",
    "maxTimeoutSeconds": 600,
    "extra": {
      "tag": 535311,
      "sessionId": "a023cfcb88cb72ab0f689ad3ab7d1e92",
      "tagModulus": 1000000,
      "expiresAt": "2026-03-03T08:07:58.154Z"
    }
  },
  "375a943c611ab3860f29a66ccad24076": {
    "scheme": "nano-session",
    "network": "nano:mainnet",
    "asset": "XNO",
    "amount": "10000000000000000000000000000",
    "payTo": "nano_39qdd16muqpz78fk5nxsaqpd1dxko54hbiic7nrirwkjei49f3ir439isxgx",
    "maxTimeoutSeconds": 600,
    "extra": {
      "tag": 691412,
      "sessionId": "375a943c611ab3860f29a66ccad24076",
      "tagModulus": 1000000,
      "expiresAt": "2026-03-03T08:08:32.480Z"
    }
  },
  "142eb1b9fba27a47ea28f1cf1cd5201f": {
    "scheme": "nano-session",
    "network": "nano:mainnet",
    "asset": "XNO",
    "amount": "10000000000000000000000000000",
    "payTo": "nano_39qdd16muqpz78fk5nxsaqpd1dxko54hbiic7nrirwkjei49f3ir439isxgx",
    "maxTimeoutSeconds": 600,
    "extra": {
      "tag": 657070,
      "sessionId": "142eb1b9fba27a47ea28f1cf1cd5201f",
      "tagModulus": 1000000,
      "expiresAt": "2026-03-03T08:08:32.499Z"
    }
  },
  "88d6c2472d34bb89f3c94380a990717e": {
    "scheme": "nano-session",
    "network": "nano:mainnet",
    "asset": "XNO",
    "amount": "10000000000000000000000000000",
    "payTo": "nano_39qdd16muqpz78fk5nxsaqpd1dxko54hbiic7nrirwkjei49f3ir439isxgx",
    "maxTimeoutSeconds": 600,
    "extra": {
      "tag": 316889,
      "sessionId": "88d6c2472d34bb89f3c94380a990717e",
      "tagModulus": 1000000,
      "expiresAt": "2026-03-03T08:24:25.090Z"
    }
  },
  "7f962c4abba7374a356a5653590e51b7": {
    "scheme": "nano-session",
    "network": "nano:mainnet",
    "asset": "XNO",
    "amount": "10000000000000000000000000000",
    "payTo": "nano_39qdd16muqpz78fk5nxsaqpd1dxko54hbiic7nrirwkjei49f3ir439isxgx",
    "maxTimeoutSeconds": 600,
    "extra": {
      "tag": 190041,
      "sessionId": "7f962c4abba7374a356a5653590e51b7",
      "tagModulus": 1000000,
      "expiresAt": "2026-03-03T08:25:09.702Z"
    }
  },
  "15fd8805f286b40b7fef936c477c4305": {
    "scheme": "nano-session",
    "network": "nano:mainnet",
    "asset": "XNO",
    "amount": "10000000000000000000000000000",
    "payTo": "nano_39qdd16muqpz78fk5nxsaqpd1dxko54hbiic7nrirwkjei49f3ir439isxgx",
    "maxTimeoutSeconds": 600,
    "extra": {
      "tag": 378183,
      "sessionId": "15fd8805f286b40b7fef936c477c4305",
      "tagModulus": 1000000,
      "expiresAt": "2026-03-03T08:25:09.707Z"
    }
  },
  "f891616ab5babb31155b5399f688e447": {
    "scheme": "nano-session",
    "network": "nano:mainnet",
    "asset": "XNO",
    "amount": "10000000000000000000000000000",
    "payTo": "nano_39qdd16muqpz78fk5nxsaqpd1dxko54hbiic7nrirwkjei49f3ir439isxgx",
    "maxTimeoutSeconds": 600,
    "extra": {
      "tag": 942965,
      "sessionId": "f891616ab5babb31155b5399f688e447",
      "tagModulus": 1000000,
      "expiresAt": "2026-03-03T08:25:09.778Z"
    }
  },
  "c91e7aa70409ac7b08947a2f507654bf": {
    "scheme": "nano-session",
    "network": "nano:mainnet",
    "asset": "XNO",
    "amount": "10000000000000000000000000000",
    "payTo": "nano_39qdd16muqpz78fk5nxsaqpd1dxko54hbiic7nrirwkjei49f3ir439isxgx",
    "maxTimeoutSeconds": 600,
    "extra": {
      "tag": 241376,
      "sessionId": "c91e7aa70409ac7b08947a2f507654bf",
      "tagModulus": 1000000,
      "expiresAt": "2026-03-03T09:25:49.172Z"
    }
  },
  "0ff5e120b694d5d57111e1683d3c25e6": {
    "scheme": "nano-session",
    "network": "nano:mainnet",
    "asset": "XNO",
    "amount": "10000000000000000000000000000",
    "payTo": "nano_39qdd16muqpz78fk5nxsaqpd1dxko54hbiic7nrirwkjei49f3ir439isxgx",
    "maxTimeoutSeconds": 600,
    "extra": {
      "tag": 374989,
      "sessionId": "0ff5e120b694d5d57111e1683d3c25e6",
      "tagModulus": 1000000,
      "expiresAt": "2026-03-03T09:33:03.694Z"
    }
  },
  "91f5e392483a9dcb3ff88db29392d7f8": {
    "scheme": "nano-session",
    "network": "nano:mainnet",
    "asset": "XNO",
    "amount": "10000000000000000000000000000",
    "payTo": "nano_39qdd16muqpz78fk5nxsaqpd1dxko54hbiic7nrirwkjei49f3ir439isxgx",
    "maxTimeoutSeconds": 600,
    "extra": {
      "tag": 478608,
      "sessionId": "91f5e392483a9dcb3ff88db29392d7f8",
      "tagModulus": 1000000,
      "expiresAt": "2026-03-03T09:34:25.682Z"
    }
  },
  "cab1346c7326605b889a583f4308afbf": {
    "scheme": "nano-session",
    "network": "nano:mainnet",
    "asset": "XNO",
    "amount": "10000000000000000000000000000",
    "payTo": "nano_39qdd16muqpz78fk5nxsaqpd1dxko54hbiic7nrirwkjei49f3ir439isxgx",
    "maxTimeoutSeconds": 600,
    "extra": {
      "tag": 65693,
      "sessionId": "cab1346c7326605b889a583f4308afbf",
      "tagModulus": 1000000,
      "expiresAt": "2026-03-03T09:34:46.366Z"
    }
  },
  "5b4dcaea00cefd0379db2b18f8d1d598": {
    "scheme": "nano-session",
    "network": "nano:mainnet",
    "asset": "XNO",
    "amount": "10000000000000000000000000000",
    "payTo": "nano_39qdd16muqpz78fk5nxsaqpd1dxko54hbiic7nrirwkjei49f3ir439isxgx",
    "maxTimeoutSeconds": 600,
    "extra": {
      "tag": 942818,
      "sessionId": "5b4dcaea00cefd0379db2b18f8d1d598",
      "tagModulus": 1000000,
      "expiresAt": "2026-03-03T09:35:00.962Z"
    }
  },
  "08c14817d071e565d69a2d07de114124": {
    "scheme": "nano-session",
    "network": "nano:mainnet",
    "asset": "XNO",
    "amount": "10000000000000000000000000000",
    "payTo": "nano_39qdd16muqpz78fk5nxsaqpd1dxko54hbiic7nrirwkjei49f3ir439isxgx",
    "maxTimeoutSeconds": 600,
    "extra": {
      "tag": 89660,
      "sessionId": "08c14817d071e565d69a2d07de114124",
      "tagModulus": 1000000,
      "expiresAt": "2026-03-03T09:35:39.088Z"
    }
  },
  "0c4c3097ae8f08f345a0335b8b77fcdf": {
    "scheme": "nano-session",
    "network": "nano:mainnet",
    "asset": "XNO",
    "amount": "10000000000000000000000000000",
    "payTo": "nano_39qdd16muqpz78fk5nxsaqpd1dxko54hbiic7nrirwkjei49f3ir439isxgx",
    "maxTimeoutSeconds": 600,
    "extra": {
      "tag": 268813,
      "sessionId": "0c4c3097ae8f08f345a0335b8b77fcdf",
      "tagModulus": 1000000,
      "expiresAt": "2026-03-03T09:36:26.503Z"
    }
  },
  "fb6b4c106dc788eec17c344541a47d14": {
    "scheme": "nano-session",
    "network": "nano:mainnet",
    "asset": "XNO",
    "amount": "10000000000000000000000000000",
    "payTo": "nano_39qdd16muqpz78fk5nxsaqpd1dxko54hbiic7nrirwkjei49f3ir439isxgx",
    "maxTimeoutSeconds": 600,
    "extra": {
      "tag": 948702,
      "sessionId": "fb6b4c106dc788eec17c344541a47d14",
      "tagModulus": 1000000,
      "expiresAt": "2026-03-03T09:36:54.882Z"
    }
  },
  "e8f78738d5f5f4bbb1cb8dcde2d6510c": {
    "scheme": "nano-session",
    "network": "nano:mainnet",
    "asset": "XNO",
    "amount": "10000000000000000000000000000",
    "payTo": "nano_39qdd16muqpz78fk5nxsaqpd1dxko54hbiic7nrirwkjei49f3ir439isxgx",
    "maxTimeoutSeconds": 600,
    "extra": {
      "tag": 493934,
      "sessionId": "e8f78738d5f5f4bbb1cb8dcde2d6510c",
      "tagModulus": 1000000,
      "expiresAt": "2026-03-03T09:37:22.557Z"
    }
  },
  "eb182d53e97370f41fb5f47fc27e4987": {
    "scheme": "nano-session",
    "network": "nano:mainnet",
    "asset": "XNO",
    "amount": "10000000000000000000000000000",
    "payTo": "nano_39qdd16muqpz78fk5nxsaqpd1dxko54hbiic7nrirwkjei49f3ir439isxgx",
    "maxTimeoutSeconds": 600,
    "extra": {
      "tag": 189143,
      "sessionId": "eb182d53e97370f41fb5f47fc27e4987",
      "tagModulus": 1000000,
      "expiresAt": "2026-03-03T09:38:14.840Z"
    }
  },
  "85df1db132681688417d8f63bf7a7522": {
    "scheme": "nano-session",
    "network": "nano:mainnet",
    "asset": "XNO",
    "amount": "10000000000000000000000000000",
    "payTo": "nano_39qdd16muqpz78fk5nxsaqpd1dxko54hbiic7nrirwkjei49f3ir439isxgx",
    "maxTimeoutSeconds": 600,
    "extra": {
      "tag": 316576,
      "sessionId": "85df1db132681688417d8f63bf7a7522",
      "tagModulus": 1000000,
      "expiresAt": "2026-03-03T09:38:27.597Z"
    }
  },
  "063a6d47357270a8243b2af415a3bef0": {
    "scheme": "nano-session",
    "network": "nano:mainnet",
    "asset": "XNO",
    "amount": "10000000000000000000000000000",
    "payTo": "nano_39qdd16muqpz78fk5nxsaqpd1dxko54hbiic7nrirwkjei49f3ir439isxgx",
    "maxTimeoutSeconds": 600,
    "extra": {
      "tag": 129979,
      "sessionId": "063a6d47357270a8243b2af415a3bef0",
      "tagModulus": 1000000,
      "expiresAt": "2026-03-03T09:54:02.837Z"
    }
  },
  "328e3be18431a9822f4ba833bd4c07b4": {
    "scheme": "nano-session",
    "network": "nano:mainnet",
    "asset": "XNO",
    "amount": "10000000000000000000000000000",
    "payTo": "nano_39qdd16muqpz78fk5nxsaqpd1dxko54hbiic7nrirwkjei49f3ir439isxgx",
    "maxTimeoutSeconds": 600,
    "extra": {
      "tag": 702666,
      "sessionId": "328e3be18431a9822f4ba833bd4c07b4",
      "tagModulus": 1000000,
      "expiresAt": "2026-03-03T09:54:24.173Z"
    }
  },
  "33c34b8e0687905a15ab2e37c2da8dda": {
    "scheme": "nano-session",
    "network": "nano:mainnet",
    "asset": "XNO",
    "amount": "10000000000000000000000000000",
    "payTo": "nano_1x4ns13z4a57bm8y11b6y4rrg8mo54ip5o3edso7y9j7hpjfcgjbkkimtemc",
    "maxTimeoutSeconds": 600,
    "extra": {
      "tag": 246140,
      "sessionId": "33c34b8e0687905a15ab2e37c2da8dda",
      "tagModulus": 1000000,
      "expiresAt": "2026-03-03T09:54:33.695Z"
    }
  },
  "bbc9af5152b5d9dfa5cfd0ed12feec2c": {
    "scheme": "nano-session",
    "network": "nano:mainnet",
    "asset": "XNO",
    "amount": "10000000000000000000000000000",
    "payTo": "nano_39qdd16muqpz78fk5nxsaqpd1dxko54hbiic7nrirwkjei49f3ir439isxgx",
    "maxTimeoutSeconds": 600,
    "extra": {
      "tag": 403565,
      "sessionId": "bbc9af5152b5d9dfa5cfd0ed12feec2c",
      "tagModulus": 1000000,
      "expiresAt": "2026-03-03T09:54:35.988Z"
    }
  },
  "c72c58620d97d0c1dba852902dd0a084": {
    "scheme": "nano-session",
    "network": "nano:mainnet",
    "asset": "XNO",
    "amount": "10000000000000000000000000000",
    "payTo": "nano_39qdd16muqpz78fk5nxsaqpd1dxko54hbiic7nrirwkjei49f3ir439isxgx",
    "maxTimeoutSeconds": 600,
    "extra": {
      "tag": 339431,
      "sessionId": "c72c58620d97d0c1dba852902dd0a084",
      "tagModulus": 1000000,
      "expiresAt": "2026-03-03T09:56:36.360Z"
    }
  },
  "8db63e8f06e7b002b25b6a97dd2afedf": {
    "scheme": "nano-session",
    "network": "nano:mainnet",
    "asset": "XNO",
    "amount": "10000000000000000000000000000",
    "payTo": "nano_39qdd16muqpz78fk5nxsaqpd1dxko54hbiic7nrirwkjei49f3ir439isxgx",
    "maxTimeoutSeconds": 600,
    "extra": {
      "tag": 133206,
      "sessionId": "8db63e8f06e7b002b25b6a97dd2afedf",
      "tagModulus": 1000000,
      "expiresAt": "2026-03-03T09:59:00.533Z"
    }
  },
  "cd23066ba6846cffae7f3fe84bd2960b": {
    "scheme": "nano-session",
    "network": "nano:mainnet",
    "asset": "XNO",
    "amount": "10000000000000000000000000000",
    "payTo": "nano_39qdd16muqpz78fk5nxsaqpd1dxko54hbiic7nrirwkjei49f3ir439isxgx",
    "maxTimeoutSeconds": 600,
    "extra": {
      "tag": 622000,
      "sessionId": "cd23066ba6846cffae7f3fe84bd2960b",
      "tagModulus": 1000000,
      "expiresAt": "2026-03-03T09:59:06.092Z"
    }
  },
  "9c96a834de1ae75b033c2497f5bce484": {
    "scheme": "nano-session",
    "network": "nano:mainnet",
    "asset": "XNO",
    "amount": "10000000000000000000000000000",
    "payTo": "nano_39qdd16muqpz78fk5nxsaqpd1dxko54hbiic7nrirwkjei49f3ir439isxgx",
    "maxTimeoutSeconds": 600,
    "extra": {
      "tag": 7583,
      "sessionId": "9c96a834de1ae75b033c2497f5bce484",
      "tagModulus": 1000000,
      "expiresAt": "2026-03-03T09:59:56.837Z"
    }
  },
  "590ee4c0af8df919c5964eec4af461e8": {
    "scheme": "nano-session",
    "network": "nano:mainnet",
    "asset": "XNO",
    "amount": "10000000000000000000000000000",
    "payTo": "nano_39qdd16muqpz78fk5nxsaqpd1dxko54hbiic7nrirwkjei49f3ir439isxgx",
    "maxTimeoutSeconds": 600,
    "extra": {
      "tag": 428972,
      "sessionId": "590ee4c0af8df919c5964eec4af461e8",
      "tagModulus": 1000000,
      "expiresAt": "2026-03-03T10:00:08.174Z"
    }
  },
  "10b8f3be959edf55dfb002cefacfeb48": {
    "scheme": "nano-session",
    "network": "nano:mainnet",
    "asset": "XNO",
    "amount": "10000000000000000000000000000",
    "payTo": "nano_39qdd16muqpz78fk5nxsaqpd1dxko54hbiic7nrirwkjei49f3ir439isxgx",
    "maxTimeoutSeconds": 600,
    "extra": {
      "tag": 375948,
      "sessionId": "10b8f3be959edf55dfb002cefacfeb48",
      "tagModulus": 1000000,
      "expiresAt": "2026-03-03T10:00:34.881Z"
    }
  },
  "dc4696bc4e9bffe95bd904b97800d83d": {
    "scheme": "nano-session",
    "network": "nano:mainnet",
    "asset": "XNO",
    "amount": "10000000000000000000000000000",
    "payTo": "nano_39qdd16muqpz78fk5nxsaqpd1dxko54hbiic7nrirwkjei49f3ir439isxgx",
    "maxTimeoutSeconds": 600,
    "extra": {
      "tag": 167592,
      "sessionId": "dc4696bc4e9bffe95bd904b97800d83d",
      "tagModulus": 1000000,
      "expiresAt": "2026-03-03T10:00:58.381Z"
    }
  },
  "6930edb23aecdb94644859313f169ad3": {
    "scheme": "nano-session",
    "network": "nano:mainnet",
    "asset": "XNO",
    "amount": "10000000000000000000000000000",
    "payTo": "nano_39qdd16muqpz78fk5nxsaqpd1dxko54hbiic7nrirwkjei49f3ir439isxgx",
    "maxTimeoutSeconds": 600,
    "extra": {
      "tag": 999766,
      "sessionId": "6930edb23aecdb94644859313f169ad3",
      "tagModulus": 1000000,
      "expiresAt": "2026-03-03T10:01:23.979Z"
    }
  },
  "b8bf8173a07219422a0289e2187aefd0": {
    "scheme": "nano-session",
    "network": "nano:mainnet",
    "asset": "XNO",
    "amount": "10000000000000000000000000000",
    "payTo": "nano_39qdd16muqpz78fk5nxsaqpd1dxko54hbiic7nrirwkjei49f3ir439isxgx",
    "maxTimeoutSeconds": 600,
    "extra": {
      "tag": 385471,
      "sessionId": "b8bf8173a07219422a0289e2187aefd0",
      "tagModulus": 1000000,
      "expiresAt": "2026-03-03T10:02:48.475Z"
    }
  },
  "df8c1a7c240bfece17977f219c11b8ea": {
    "scheme": "nano-session",
    "network": "nano:mainnet",
    "asset": "XNO",
    "amount": "10000000000000000000000000000",
    "payTo": "nano_39qdd16muqpz78fk5nxsaqpd1dxko54hbiic7nrirwkjei49f3ir439isxgx",
    "maxTimeoutSeconds": 600,
    "extra": {
      "tag": 650991,
      "sessionId": "df8c1a7c240bfece17977f219c11b8ea",
      "tagModulus": 1000000,
      "expiresAt": "2026-03-03T10:05:01.892Z"
    }
  },
  "eb692f0766e64fdfb2413ccda0e056af": {
    "scheme": "nano-session",
    "network": "nano:mainnet",
    "asset": "XNO",
    "amount": "10000000000000000000000000000",
    "payTo": "nano_39qdd16muqpz78fk5nxsaqpd1dxko54hbiic7nrirwkjei49f3ir439isxgx",
    "maxTimeoutSeconds": 600,
    "extra": {
      "tag": 798673,
      "sessionId": "eb692f0766e64fdfb2413ccda0e056af",
      "tagModulus": 1000000,
      "expiresAt": "2026-03-03T10:05:18.607Z"
    }
  },
  "134ac892e433e6d7a3ea08c2a3997526": {
    "scheme": "nano-session",
    "network": "nano:mainnet",
    "asset": "XNO",
    "amount": "10000000000000000000000000000",
    "payTo": "nano_39qdd16muqpz78fk5nxsaqpd1dxko54hbiic7nrirwkjei49f3ir439isxgx",
    "maxTimeoutSeconds": 600,
    "extra": {
      "tag": 303719,
      "sessionId": "134ac892e433e6d7a3ea08c2a3997526",
      "tagModulus": 1000000,
      "expiresAt": "2026-03-03T10:11:11.214Z"
    }
  },
  "36da4e0386375f8361a1cd8791639cd4": {
    "scheme": "nano-session",
    "network": "nano:mainnet",
    "asset": "XNO",
    "amount": "10000000000000000000000000000",
    "payTo": "nano_39qdd16muqpz78fk5nxsaqpd1dxko54hbiic7nrirwkjei49f3ir439isxgx",
    "maxTimeoutSeconds": 600,
    "extra": {
      "tag": 928886,
      "sessionId": "36da4e0386375f8361a1cd8791639cd4",
      "tagModulus": 1000000,
      "expiresAt": "2026-03-03T10:12:26.700Z"
    }
  },
  "4c6331f6a6c54c4196f37b2f01802235": {
    "scheme": "nano-session",
    "network": "nano:mainnet",
    "asset": "XNO",
    "amount": "10000000000000000000000000000",
    "payTo": "nano_39qdd16muqpz78fk5nxsaqpd1dxko54hbiic7nrirwkjei49f3ir439isxgx",
    "maxTimeoutSeconds": 600,
    "extra": {
      "tag": 744068,
      "sessionId": "4c6331f6a6c54c4196f37b2f01802235",
      "tagModulus": 1000000,
      "expiresAt": "2026-03-03T10:28:08.717Z"
    }
  },
  "1bc357fb05e9c8d98c0505dc52ba88a7": {
    "scheme": "nano-session",
    "network": "nano:mainnet",
    "asset": "XNO",
    "amount": "10000000000000000000000000000",
    "payTo": "nano_39qdd16muqpz78fk5nxsaqpd1dxko54hbiic7nrirwkjei49f3ir439isxgx",
    "maxTimeoutSeconds": 600,
    "extra": {
      "tag": 358537,
      "sessionId": "1bc357fb05e9c8d98c0505dc52ba88a7",
      "tagModulus": 1000000,
      "expiresAt": "2026-03-03T10:28:12.529Z"
    }
  },
  "1ede0c24dcfff3c1a0768138789d8a47": {
    "scheme": "nano-session",
    "network": "nano:mainnet",
    "asset": "XNO",
    "amount": "10000000000000000000000000000",
    "payTo": "nano_39qdd16muqpz78fk5nxsaqpd1dxko54hbiic7nrirwkjei49f3ir439isxgx",
    "maxTimeoutSeconds": 600,
    "extra": {
      "tag": 46430,
      "sessionId": "1ede0c24dcfff3c1a0768138789d8a47",
      "tagModulus": 1000000,
      "expiresAt": "2026-03-03T10:28:36.523Z"
    }
  },
  "5ce948b53958cdab0e1b537fddc220af": {
    "scheme": "nano-session",
    "network": "nano:mainnet",
    "asset": "XNO",
    "amount": "10000000000000000000000000000",
    "payTo": "nano_39qdd16muqpz78fk5nxsaqpd1dxko54hbiic7nrirwkjei49f3ir439isxgx",
    "maxTimeoutSeconds": 600,
    "extra": {
      "tag": 855164,
      "sessionId": "5ce948b53958cdab0e1b537fddc220af",
      "tagModulus": 1000000,
      "expiresAt": "2026-03-03T10:30:19.648Z"
    }
  },
  "493901a89d389dd30dddf858086995ba": {
    "scheme": "nano-session",
    "network": "nano:mainnet",
    "asset": "XNO",
    "amount": "10000000000000000000000000000",
    "payTo": "nano_39qdd16muqpz78fk5nxsaqpd1dxko54hbiic7nrirwkjei49f3ir439isxgx",
    "maxTimeoutSeconds": 600,
    "extra": {
      "tag": 922294,
      "sessionId": "493901a89d389dd30dddf858086995ba",
      "tagModulus": 1000000,
      "expiresAt": "2026-03-03T10:47:29.127Z"
    }
  },
  "e6cc1a494dc098fdcc1e803fbf9497e1": {
    "scheme": "nano-session",
    "network": "nano:mainnet",
    "asset": "XNO",
    "amount": "10000000000000000000000000000",
    "payTo": "nano_39qdd16muqpz78fk5nxsaqpd1dxko54hbiic7nrirwkjei49f3ir439isxgx",
    "maxTimeoutSeconds": 600,
    "extra": {
      "tag": 275915,
      "sessionId": "e6cc1a494dc098fdcc1e803fbf9497e1",
      "tagModulus": 1000000,
      "expiresAt": "2026-03-03T10:47:37.365Z"
    }
  },
  "61712ef964c2915612873d24be294d34": {
    "scheme": "nano-session",
    "network": "nano:mainnet",
    "asset": "XNO",
    "amount": "10000000000000000000000000000",
    "payTo": "nano_39qdd16muqpz78fk5nxsaqpd1dxko54hbiic7nrirwkjei49f3ir439isxgx",
    "maxTimeoutSeconds": 600,
    "extra": {
      "tag": 247348,
      "sessionId": "61712ef964c2915612873d24be294d34",
      "tagModulus": 1000000,
      "expiresAt": "2026-03-03T10:47:41.718Z"
    }
  },
  "f8bed38162580cd5d587a46f84e3036d": {
    "scheme": "nano-session",
    "network": "nano:mainnet",
    "asset": "XNO",
    "amount": "10000000000000000000000000000",
    "payTo": "nano_39qdd16muqpz78fk5nxsaqpd1dxko54hbiic7nrirwkjei49f3ir439isxgx",
    "maxTimeoutSeconds": 600,
    "extra": {
      "tag": 127602,
      "sessionId": "f8bed38162580cd5d587a46f84e3036d",
      "tagModulus": 1000000,
      "expiresAt": "2026-03-03T10:47:44.307Z"
    }
  },
  "0d771d2806163dd3610f1a71f0ce5c2a": {
    "scheme": "nano-session",
    "network": "nano:mainnet",
    "asset": "XNO",
    "amount": "10000000000000000000000000000",
    "payTo": "nano_39qdd16muqpz78fk5nxsaqpd1dxko54hbiic7nrirwkjei49f3ir439isxgx",
    "maxTimeoutSeconds": 600,
    "extra": {
      "tag": 118970,
      "sessionId": "0d771d2806163dd3610f1a71f0ce5c2a",
      "tagModulus": 1000000,
      "expiresAt": "2026-03-03T10:48:09.510Z"
    }
  }
}